pulpcore/__init__.py
pulpcore/client/__init__.py
pulpcore/client/pulp_2to3_migration/__init__.py
pulpcore/client/pulp_2to3_migration/api_client.py
pulpcore/client/pulp_2to3_migration/configuration.py
pulpcore/client/pulp_2to3_migration/exceptions.py
pulpcore/client/pulp_2to3_migration/rest.py
pulpcore/client/pulp_2to3_migration/api/__init__.py
pulpcore/client/pulp_2to3_migration/api/migration_plans_api.py
pulpcore/client/pulp_2to3_migration/api/pulp2_content_api.py
pulpcore/client/pulp_2to3_migration/api/pulp2_repositories_api.py
pulpcore/client/pulp_2to3_migration/models/__init__.py
pulpcore/client/pulp_2to3_migration/models/async_operation_response.py
pulpcore/client/pulp_2to3_migration/models/migration_plan_run.py
pulpcore/client/pulp_2to3_migration/models/paginatedpulp2to3_migration_migration_plan_response_list.py
pulpcore/client/pulp_2to3_migration/models/paginatedpulp2to3_migration_pulp2_content_response_list.py
pulpcore/client/pulp_2to3_migration/models/paginatedpulp2to3_migration_pulp2_repository_response_list.py
pulpcore/client/pulp_2to3_migration/models/pulp2to3_migration_migration_plan.py
pulpcore/client/pulp_2to3_migration/models/pulp2to3_migration_migration_plan_response.py
pulpcore/client/pulp_2to3_migration/models/pulp2to3_migration_pulp2_content_response.py
pulpcore/client/pulp_2to3_migration/models/pulp2to3_migration_pulp2_repository_response.py
pulp_2to3_migration_client-0.16.0.dist-info/METADATA
pulp_2to3_migration_client-0.16.0.dist-info/WHEEL
pulp_2to3_migration_client-0.16.0.dist-info/top_level.txt
pulp_2to3_migration_client-0.16.0.dist-info/RECORD
